pyoptex-1.0.3.dist-info/RECORD
pyoptex-1.0.3.dist-info/WHEEL
pyoptex-1.0.3.dist-info/top_level.txt
pyoptex-1.0.3.dist-info/METADATA
pyoptex-1.0.3.dist-info/licenses/LICENSE
pyoptex/_seed_cy.pypy310-pp73-darwin.so
pyoptex/_profile.py
pyoptex/__init__.py
pyoptex/_seed.py
pyoptex/_seed_cy.c
pyoptex/analysis/__init__.py
pyoptex/analysis/mixins/conditional_mixin.py
pyoptex/analysis/mixins/__init__.py
pyoptex/analysis/mixins/fit_mixin.py
pyoptex/analysis/utils/plot.py
pyoptex/analysis/utils/fit.py
pyoptex/analysis/utils/__init__.py
pyoptex/analysis/transformers/__init__.py
pyoptex/analysis/transformers/quantile_outlier_transformer.py
pyoptex/analysis/estimators/simple_model.py
pyoptex/analysis/estimators/__init__.py
pyoptex/analysis/estimators/p_value_drop_model.py
pyoptex/analysis/estimators/sams/simulation.py
pyoptex/analysis/estimators/sams/plot.py
pyoptex/analysis/estimators/sams/__init__.py
pyoptex/analysis/estimators/sams/accept.py
pyoptex/analysis/estimators/sams/estimator.py
pyoptex/analysis/estimators/sams/entropy.py
pyoptex/analysis/estimators/sams/models/ols_model.py
pyoptex/analysis/estimators/sams/models/__init__.py
pyoptex/analysis/estimators/sams/models/model.py
pyoptex/analysis/estimators/sams/models/mixed_lm_model.py
pyoptex/analysis/estimators/sams/bnb/__init__.py
pyoptex/analysis/estimators/sams/bnb/sams_bnb.py
pyoptex/analysis/estimators/sams/bnb/bnb.py
pyoptex/utils/comp.py
pyoptex/utils/_design_cy.pypy310-pp73-darwin.so
pyoptex/utils/_comp_cy.pypy310-pp73-darwin.so
pyoptex/utils/design.py
pyoptex/utils/__init__.py
pyoptex/utils/_design_cy.c
pyoptex/utils/runtime.py
pyoptex/utils/model.py
pyoptex/utils/factor.py
pyoptex/utils/_comp_cy.c
pyoptex/doe/__init__.py
pyoptex/doe/constraints.py
pyoptex/doe/cost_optimal/_utils_cy.pypy310-pp73-darwin.so
pyoptex/doe/cost_optimal/_utils_cy.c
pyoptex/doe/cost_optimal/__init__.py
pyoptex/doe/cost_optimal/cov.py
pyoptex/doe/cost_optimal/metric.py
pyoptex/doe/cost_optimal/utils.py
pyoptex/doe/cost_optimal/evaluate.py
pyoptex/doe/cost_optimal/cost.py
pyoptex/doe/cost_optimal/init.py
pyoptex/doe/cost_optimal/validation.py
