Metadata-Version: 2.4
Name: pyoptex
Version: 1.0.3
Summary: Flexible and accessible design of experiments in Python. Provides industry with an easy package to create designs based with limited expert knowledge. Provides researchers with the ability to easily create new criteria and design structures.
Author-email: Mathias Born <mathiasborn2@gmail.com>
License-Expression: BSD-3-Clause
Project-URL: Homepage, https://github.com/mborn1/pyoptex
Project-URL: Documentation, https://pyoptex.readthedocs.io/en/latest/
Project-URL: Repository, https://github.com/mborn1/pyoptex
Project-URL: Issues, https://github.com/mborn1/pyoptex/issues
Keywords: python,flexible,accessible,data-analysis,design-of-experiments,pyoptex,innovation,cost-optimization
Classifier: Programming Language :: Python :: 3
Classifier: Operating System :: OS Independent
Requires-Python: >=3.10
License-File: LICENSE
Requires-Dist: numba~=0.61
Requires-Dist: numpy<3.0.0,>=2.0.0rc1
Requires-Dist: tqdm~=4.64
Requires-Dist: scipy<2.0.0,>=1.12.0
Requires-Dist: pandas~=2.0
Requires-Dist: plotly~=5.24
Requires-Dist: openpyxl~=3.1
Requires-Dist: kaleido==0.2.1; sys_platform != "win32"
Requires-Dist: kaleido==0.1.0.post1; sys_platform == "win32"
Requires-Dist: scikit-learn~=1.3
Requires-Dist: statsmodels~=0.14
Requires-Dist: ruptures~=1.1
Provides-Extra: dev
Requires-Dist: sphinx==7.1.2; extra == "dev"
Requires-Dist: sphinx-rtd-theme==1.3.0rc1; extra == "dev"
Requires-Dist: sphinx-copybutton==0.5.2; extra == "dev"
Requires-Dist: setuptools>=61.0; extra == "dev"
Requires-Dist: Cython~=3.0.12; extra == "dev"
Requires-Dist: build; extra == "dev"
Dynamic: license-file
